<?xml version="1.0" encoding="utf-8" standalone="no"?>
<!DOCTYPE Archive SYSTEM "https://greenstone.org/dtd/Archive/1.0/Archive.dtd">
<Archive>
<Section>
  <Description>
    <Metadata name="gsdlsourcefilename">import\QWxidW1z\MDYgLSBUaGUgSHVudGluZyBQYXJ0eSAoMjAxNCk=\MDggLSBSZWJlbGxpb24gRmVhdC4gRGFyb24gTWFsYWtpYW4=.mp3</Metadata>
    <Metadata name="gsdlsourcefilerenamemethod">base64</Metadata>
    <Metadata name="gsdldoctype">indexed_doc</Metadata>
    <Metadata name="Plugin">MP3Plugin</Metadata>
    <Metadata name="FileSize">8971872</Metadata>
    <Metadata name="Source">08 - Rebellion Feat. Daron Malakian.mp3</Metadata>
    <Metadata name="SourceFile">MDggLSBSZWJlbGxpb24gRmVhdC4gRGFyb24gTWFsYWtpYW4=.mp3</Metadata>
    <Metadata name="mp3">08 - Rebellion Feat. Daron Malakian</Metadata>
    <Metadata name="srcurl">MDggLSBSZWJlbGxpb24gRmVhdC4gRGFyb24gTWFsYWtpYW4=.mp3</Metadata>
    <Metadata name="ex.id3.Title">Rebellion Feat. Daron Malakian</Metadata>
    <Metadata name="ex.id3.Artist">Linkin Park</Metadata>
    <Metadata name="ex.id3.Genre">Alternative</Metadata>
    <Metadata name="FileFormat">MP3</Metadata>
    <Metadata name="srcicon">_iconmp3_</Metadata>
    <Metadata name="srclink_file">MDggLSBSZWJlbGxpb24gRmVhdC4gRGFyb24gTWFsYWtpYW4=.mp3</Metadata>
    <Metadata name="srclinkFile">MDggLSBSZWJlbGxpb24gRmVhdC4gRGFyb24gTWFsYWtpYW4=.mp3</Metadata>
    <Metadata name="NoText">1</Metadata>
    <Metadata name="dc.Subject">Linkin Park | Albums | The Hunting Party</Metadata>
    <Metadata name="Title">Rebellion Feat. Daron Malakian</Metadata>
    <Metadata name="Identifier">HASH01bb48c2e89f9d9baec8d10e</Metadata>
    <Metadata name="lastmodified">1726240136</Metadata>
    <Metadata name="lastmodifieddate">20240913</Metadata>
    <Metadata name="oailastmodified">1726242849</Metadata>
    <Metadata name="oailastmodifieddate">20240913</Metadata>
    <Metadata name="assocfilepath">HASH01bb/48c2e89f.dir</Metadata>
    <Metadata name="gsdlassocfile">MDggLSBSZWJlbGxpb24gRmVhdC4gRGFyb24gTWFsYWtpYW4=.mp3:audio/mp3:</Metadata>
  </Description>
  <Content>This document has no text.</Content>
</Section>
</Archive>
