<?xml version="1.0" encoding="utf-8" standalone="no"?>
<!DOCTYPE Archive SYSTEM "https://greenstone.org/dtd/Archive/1.0/Archive.dtd">
<Archive>
<Section>
  <Description>
    <Metadata name="gsdlsourcefilename">import\QWxidW1z\MDUgLSBMaXZpbmcgVGhpbmdzICgyMDEyKQ==\MDkgLSBTS0lOIFRPIEJPTkU=.mp3</Metadata>
    <Metadata name="gsdlsourcefilerenamemethod">base64</Metadata>
    <Metadata name="gsdldoctype">indexed_doc</Metadata>
    <Metadata name="Plugin">MP3Plugin</Metadata>
    <Metadata name="FileSize">6739871</Metadata>
    <Metadata name="Source">09 - SKIN TO BONE.mp3</Metadata>
    <Metadata name="SourceFile">MDkgLSBTS0lOIFRPIEJPTkU=.mp3</Metadata>
    <Metadata name="mp3">09 - SKIN TO BONE</Metadata>
    <Metadata name="srcurl">MDkgLSBTS0lOIFRPIEJPTkU=.mp3</Metadata>
    <Metadata name="ex.id3.Title">SKIN TO BONE</Metadata>
    <Metadata name="ex.id3.Artist">Linkin Park</Metadata>
    <Metadata name="ex.id3.Genre">Alternative</Metadata>
    <Metadata name="FileFormat">MP3</Metadata>
    <Metadata name="srcicon">_iconmp3_</Metadata>
    <Metadata name="srclink_file">MDkgLSBTS0lOIFRPIEJPTkU=.mp3</Metadata>
    <Metadata name="srclinkFile">MDkgLSBTS0lOIFRPIEJPTkU=.mp3</Metadata>
    <Metadata name="NoText">1</Metadata>
    <Metadata name="dc.Creator">Petar Milchevski</Metadata>
    <Metadata name="dc.Date">2012-06-20</Metadata>
    <Metadata name="dc.FolderOrder">19</Metadata>
    <Metadata name="dc.Order">10</Metadata>
    <Metadata name="dc.Producer">Rick Rubin</Metadata>
    <Metadata name="dc.Producer">Mike Shinoda</Metadata>
    <Metadata name="dc.Publisher">Warner Bros. Records</Metadata>
    <Metadata name="dc.Studio">NRG Recording Studions</Metadata>
    <Metadata name="dc.Subject">Linkin Park | Albums | 05 Living Things</Metadata>
    <Metadata name="dc.Title">Skin To Bone</Metadata>
    <Metadata name="Title">SKIN TO BONE</Metadata>
    <Metadata name="Identifier">HASH01a564eaaaae5a683f653aec</Metadata>
    <Metadata name="lastmodified">1726240141</Metadata>
    <Metadata name="lastmodifieddate">20240913</Metadata>
    <Metadata name="oailastmodified">1727136619</Metadata>
    <Metadata name="oailastmodifieddate">20240924</Metadata>
    <Metadata name="assocfilepath">HASH01a5.dir</Metadata>
    <Metadata name="gsdlassocfile">MDkgLSBTS0lOIFRPIEJPTkU=.mp3:audio/mp3:</Metadata>
  </Description>
  <Content>This document has no text.</Content>
</Section>
</Archive>
