<?xml version="1.0" encoding="utf-8" standalone="no"?>
<!DOCTYPE Archive SYSTEM "https://greenstone.org/dtd/Archive/1.0/Archive.dtd">
<Archive>
<Section>
  <Description>
    <Metadata name="gsdlsourcefilename">import\QWxidW1z\MDQgLSBBIFRob3VzYW5kIFN1bnMgKDIwMTAp\MTEgLSBXaXNkb20sIEp1c3RpY2UsIEFuZCBMb3Zl.mp3</Metadata>
    <Metadata name="gsdlsourcefilerenamemethod">base64</Metadata>
    <Metadata name="gsdldoctype">indexed_doc</Metadata>
    <Metadata name="Plugin">MP3Plugin</Metadata>
    <Metadata name="FileSize">3960206</Metadata>
    <Metadata name="Source">11 - Wisdom, Justice, And Love.mp3</Metadata>
    <Metadata name="SourceFile">MTEgLSBXaXNkb20sIEp1c3RpY2UsIEFuZCBMb3Zl.mp3</Metadata>
    <Metadata name="mp3">11 - Wisdom, Justice, And Love</Metadata>
    <Metadata name="srcurl">MTEgLSBXaXNkb20sIEp1c3RpY2UsIEFuZCBMb3Zl.mp3</Metadata>
    <Metadata name="ex.id3.Title">Wisdom, Justice, And Love</Metadata>
    <Metadata name="ex.id3.Artist">Linkin Park</Metadata>
    <Metadata name="ex.id3.Genre">Alternative</Metadata>
    <Metadata name="FileFormat">MP3</Metadata>
    <Metadata name="srcicon">_iconmp3_</Metadata>
    <Metadata name="srclink_file">MTEgLSBXaXNkb20sIEp1c3RpY2UsIEFuZCBMb3Zl.mp3</Metadata>
    <Metadata name="srclinkFile">MTEgLSBXaXNkb20sIEp1c3RpY2UsIEFuZCBMb3Zl.mp3</Metadata>
    <Metadata name="NoText">1</Metadata>
    <Metadata name="dc.Creator">Petar Milchevski</Metadata>
    <Metadata name="dc.Date">2010-09-13</Metadata>
    <Metadata name="dc.Description">12</Metadata>
    <Metadata name="dc.FolderOrder">12</Metadata>
    <Metadata name="dc.Order">12</Metadata>
    <Metadata name="dc.Producer">Rick Rubin</Metadata>
    <Metadata name="dc.Producer">Mike Shinoda</Metadata>
    <Metadata name="dc.Publisher">Warner Bros. Records</Metadata>
    <Metadata name="dc.Studio">NRG Recording Studions</Metadata>
    <Metadata name="dc.Subject">Linkin Park | Albums | 04 A Thousand Suns</Metadata>
    <Metadata name="dc.Title">Wisdom, Justice, And Love</Metadata>
    <Metadata name="Title">Wisdom, Justice, And Love</Metadata>
    <Metadata name="Identifier">HASH0130f266d73399ca88a34d8f</Metadata>
    <Metadata name="lastmodified">1726240148</Metadata>
    <Metadata name="lastmodifieddate">20240913</Metadata>
    <Metadata name="oailastmodified">1727136616</Metadata>
    <Metadata name="oailastmodifieddate">20240924</Metadata>
    <Metadata name="assocfilepath">HASH0130.dir</Metadata>
    <Metadata name="gsdlassocfile">MTEgLSBXaXNkb20sIEp1c3RpY2UsIEFuZCBMb3Zl.mp3:audio/mp3:</Metadata>
  </Description>
  <Content>This document has no text.</Content>
</Section>
</Archive>
